nectar_msi/__init__.py
nectar_msi/_version.py
nectar_msi/main.py
nectar_msi/data_formats/__init__.py
nectar_msi/data_formats/data_cube.py
nectar_msi/data_formats/data_spectrum.py
nectar_msi/data_processing/__init__.py
nectar_msi/data_processing/data_operations.py
nectar_msi/data_processing/readers.py
nectar_msi/data_processing/savers.py
nectar_msi/database_matching/__init__.py
nectar_msi/database_matching/database_matching.py
nectar_msi/gaussian_fitting/__init__.py
nectar_msi/gaussian_fitting/gaussian_fitting.py
nectar_msi/gaussian_fitting/gaussian_fitting_definitions.py
nectar_msi/noise_correction/__init__.py
nectar_msi/noise_correction/background_noise.py
nectar_msi/noise_correction/chemical_noise.py
nectar_msi/noise_correction/noise_correction.py
nectar_msi/noise_correction/noise_determination.py
nectar_msi/peak_picking/__init__.py
nectar_msi/peak_picking/peak_picking.py
nectar_msi/plotting/__init__.py
nectar_msi/plotting/plotting.py
sample test/__init__.py
nectar_msi-0.0.6.dist-info/LICENSE
nectar_msi-0.0.6.dist-info/METADATA
nectar_msi-0.0.6.dist-info/WHEEL
nectar_msi-0.0.6.dist-info/top_level.txt
nectar_msi-0.0.6.dist-info/RECORD
