Metadata-Version: 2.1
Name: nectar-msi
Version: 0.0.6
Summary: NECTAR_MSI (NoisE CorrecTion AlgoRithm) a python package for noise determination and correction in MSI.
Home-page: https://gitlab.npl.co.uk/nice-msi/nectar
Author: Ariadna Gonzalez-Fernandez
Author-email: ariadna.gonzalez@npl.co.uk
License: GNU Lesser General Public License v3.0
Classifier: Development Status :: 2 - Pre-Alpha
Classifier: Programming Language :: Python
Classifier: Programming Language :: Python :: 3.6
Classifier: Programming Language :: Python :: 3.7
Classifier: Programming Language :: Python :: 3.8
License-File: LICENSE
Requires-Dist: numpy
Requires-Dist: matplotlib
Requires-Dist: pyimzml
Requires-Dist: h5py
Requires-Dist: scipy
Requires-Dist: pandas
Requires-Dist: scikit-learn
Requires-Dist: tqdm
Provides-Extra: dev
Requires-Dist: pre-commit ; extra == 'dev'
Requires-Dist: tox ; extra == 'dev'
Requires-Dist: sphinx ; extra == 'dev'
Requires-Dist: sphinx-rtd-theme ; extra == 'dev'
Requires-Dist: jupyter ; extra == 'dev'
